pgpython/__init__.py
pgpython/base.py
pgpython/fields.py
pgpython/pgdb.py
pgpython/schema.py
pgpython-0.8.dist-info/LICENSE
pgpython-0.8.dist-info/METADATA
pgpython-0.8.dist-info/WHEEL
pgpython-0.8.dist-info/top_level.txt
pgpython-0.8.dist-info/RECORD
